nbconvert_utils/__init__.py
nbconvert_utils/_version.py
nbconvert_utils-0.2.dist-info/METADATA
nbconvert_utils-0.2.dist-info/RECORD
nbconvert_utils-0.2.dist-info/WHEEL
nbconvert_utils-0.2.dist-info/top_level.txt
